quickplug/__init__.py
quickplug/cli.py
quickplug-0.0.1.dist-info/LICENSE
quickplug-0.0.1.dist-info/METADATA
quickplug-0.0.1.dist-info/WHEEL
quickplug-0.0.1.dist-info/top_level.txt
quickplug-0.0.1.dist-info/RECORD
