Metadata-Version: 2.1
Name: quickplug
Version: 0.0.1
Summary: A general purpose plugin framework for rapid application development and extensibility.
Home-page: https://github.com/cfekete93/quickplug
Author: Christopher S. Fekete
Author-email: cfekete93@hotmail.com
License: UNKNOWN
Platform: UNKNOWN
Classifier: Programming Language :: Python :: 3
Classifier: License :: OSI Approved :: MIT License
Classifier: Operating System :: OS Independent
Classifier: Development Status :: 1 - Planning
